grasp/__init__.py
grasp/cli.py
grasp/configs.py
grasp/core.py
grasp/evaluate.py
grasp/examples.py
grasp/functions.py
grasp/model.py
grasp/utils.py
grasp/adapt/__init__.py
grasp/adapt/note_taking.py
grasp/adapt/notes.py
grasp/adapt/utils.py
grasp/build/__init__.py
grasp/build/data.py
grasp/build/index.py
grasp/manager/__init__.py
grasp/manager/mapping.py
grasp/manager/utils.py
grasp/sparql/__init__.py
grasp/sparql/item.py
grasp/sparql/metrics.py
grasp/sparql/types.py
grasp/sparql/utils.py
grasp/tasks/__init__.py
grasp/tasks/cea.py
grasp/tasks/feedback.py
grasp/tasks/general_qa.py
grasp/tasks/sparql_qa.py
grasp/tasks/sparql_qa_examples.py
grasp/tasks/tab_to_kg_linking.py
grasp/tasks/utils.py
grasp_rdf-0.1.1.dist-info/licenses/LICENSE
grasp_rdf-0.1.1.dist-info/METADATA
grasp_rdf-0.1.1.dist-info/WHEEL
grasp_rdf-0.1.1.dist-info/entry_points.txt
grasp_rdf-0.1.1.dist-info/top_level.txt
grasp_rdf-0.1.1.dist-info/RECORD
