Metadata-Version: 2.4
Name: grasp-rdf
Version: 0.1.1
Summary: GRASP: Generic Reasoning and SPARQL generation across knowledge graphs
Author-email: Sebastian Walter <swalter@cs.uni-freiburg.de>
Project-URL: Github, https://github.com/bastiscode/grasp
Keywords: rdf,llm,sparql,question answering,knowledge graph
Classifier: Programming Language :: Python :: 3
Classifier: Topic :: Scientific/Engineering :: Artificial Intelligence
Classifier: Topic :: Text Processing
Classifier: Topic :: Utilities
Requires-Python: >=3.12
License-File: LICENSE
Requires-Dist: pydantic>=2.9.0
Requires-Dist: litellm>=1.65
Requires-Dist: requests>=2.32.0
Requires-Dist: tqdm>=4.65.0
Requires-Dist: validators>=0.34.0
Requires-Dist: scipy>=1.15.0
Requires-Dist: universal-ml-utils>=0.1.3
Requires-Dist: grammar-utils>=0.1.3
Requires-Dist: search-index>=0.4.0
Requires-Dist: fastapi>=0.115.0
Requires-Dist: uvicorn>=0.30.0
Requires-Dist: websockets>=14.0
Provides-Extra: data
Requires-Dist: datasets>=3.3.0; extra == "data"
Requires-Dist: beautifulsoup4>=4.12.0; extra == "data"
Dynamic: license-file
